openplantbook_sdk/__init__.py
openplantbook_sdk/sdk.py
openplantbook_sdk-0.5.0.dist-info/licenses/LICENSE
openplantbook_sdk-0.5.0.dist-info/METADATA
openplantbook_sdk-0.5.0.dist-info/WHEEL
openplantbook_sdk-0.5.0.dist-info/top_level.txt
openplantbook_sdk-0.5.0.dist-info/RECORD
