Metadata-Version: 2.4
Name: openplantbook-sdk
Version: 0.5.0
Summary: Open Plantbook SDK for Python
Home-page: https://github.com/slaxor505/openplantbook-sdk-py
Author: Slava Pisarevskiy
Author-email: slava@plantbook.io
License: "MIT"
Project-URL: Documentation, https://openplantbook-sdk-py.readthedocs.io
Project-URL: Source, https://github.com/slaxor505/openplantbook-sdk-py
Keywords: json,timeseries,iot,jts
Classifier: Intended Audience :: Developers
Classifier: Programming Language :: Python
Classifier: Programming Language :: Python :: 3
Classifier: Programming Language :: Python :: 3.9
Classifier: Operating System :: OS Independent
Requires-Python: >=3.9
License-File: LICENSE
Requires-Dist: aiohttp
Requires-Dist: json-timeseries
Dynamic: license-file
